<annotation>
	<folder>images</folder>
	<filename>286.jpg</filename>
	<path>/home/dcampoamor/tensorflow_frutas_environment/deteccion_objetos/images/286.jpg</path>
	<source>
		<database>Unknown</database>
	</source>
	<size>
		<width>612</width>
		<height>408</height>
		<depth>3</depth>
	</size>
	<segmented>0</segmented>
	<object>
		<name>Fresa</name>
		<pose>Unspecified</pose>
		<truncated>0</truncated>
		<difficult>0</difficult>
		<bndbox>
			<xmin>76</xmin>
			<ymin>83</ymin>
			<xmax>347</xmax>
			<ymax>370</ymax>
		</bndbox>
	</object>
	<object>
		<name>Fresa</name>
		<pose>Unspecified</pose>
		<truncated>0</truncated>
		<difficult>0</difficult>
		<bndbox>
			<xmin>279</xmin>
			<ymin>71</ymin>
			<xmax>494</xmax>
			<ymax>313</ymax>
		</bndbox>
	</object>
</annotation>
