<annotation>
	<folder>images</folder>
	<filename>735.jpg</filename>
	<path>/home/dcampoamor/tensorflow_frutas_environment/deteccion_objetos/images/735.jpg</path>
	<source>
		<database>Unknown</database>
	</source>
	<size>
		<width>390</width>
		<height>260</height>
		<depth>3</depth>
	</size>
	<segmented>0</segmented>
	<object>
		<name>Fresa</name>
		<pose>Unspecified</pose>
		<truncated>0</truncated>
		<difficult>0</difficult>
		<bndbox>
			<xmin>42</xmin>
			<ymin>162</ymin>
			<xmax>138</xmax>
			<ymax>255</ymax>
		</bndbox>
	</object>
	<object>
		<name>Fresa</name>
		<pose>Unspecified</pose>
		<truncated>0</truncated>
		<difficult>0</difficult>
		<bndbox>
			<xmin>123</xmin>
			<ymin>118</ymin>
			<xmax>257</xmax>
			<ymax>238</ymax>
		</bndbox>
	</object>
	<object>
		<name>Fresa</name>
		<pose>Unspecified</pose>
		<truncated>0</truncated>
		<difficult>0</difficult>
		<bndbox>
			<xmin>266</xmin>
			<ymin>108</ymin>
			<xmax>382</xmax>
			<ymax>231</ymax>
		</bndbox>
	</object>
	<object>
		<name>Fresa</name>
		<pose>Unspecified</pose>
		<truncated>0</truncated>
		<difficult>0</difficult>
		<bndbox>
			<xmin>179</xmin>
			<ymin>43</ymin>
			<xmax>296</xmax>
			<ymax>162</ymax>
		</bndbox>
	</object>
</annotation>
