<annotation>
	<folder>images</folder>
	<filename>97.jpg</filename>
	<path>/home/dcampoamor/tensorflow_frutas_environment/deteccion_objetos/images/97.jpg</path>
	<source>
		<database>Unknown</database>
	</source>
	<size>
		<width>120</width>
		<height>120</height>
		<depth>3</depth>
	</size>
	<segmented>0</segmented>
	<object>
		<name>Fresa</name>
		<pose>Unspecified</pose>
		<truncated>1</truncated>
		<difficult>0</difficult>
		<bndbox>
			<xmin>11</xmin>
			<ymin>1</ymin>
			<xmax>45</xmax>
			<ymax>24</ymax>
		</bndbox>
	</object>
	<object>
		<name>Fresa</name>
		<pose>Unspecified</pose>
		<truncated>0</truncated>
		<difficult>0</difficult>
		<bndbox>
			<xmin>27</xmin>
			<ymin>17</ymin>
			<xmax>62</xmax>
			<ymax>52</ymax>
		</bndbox>
	</object>
	<object>
		<name>Fresa</name>
		<pose>Unspecified</pose>
		<truncated>1</truncated>
		<difficult>0</difficult>
		<bndbox>
			<xmin>1</xmin>
			<ymin>11</ymin>
			<xmax>18</xmax>
			<ymax>45</ymax>
		</bndbox>
	</object>
	<object>
		<name>Fresa</name>
		<pose>Unspecified</pose>
		<truncated>0</truncated>
		<difficult>0</difficult>
		<bndbox>
			<xmin>60</xmin>
			<ymin>11</ymin>
			<xmax>87</xmax>
			<ymax>43</ymax>
		</bndbox>
	</object>
	<object>
		<name>Fresa</name>
		<pose>Unspecified</pose>
		<truncated>1</truncated>
		<difficult>0</difficult>
		<bndbox>
			<xmin>99</xmin>
			<ymin>11</ymin>
			<xmax>120</xmax>
			<ymax>43</ymax>
		</bndbox>
	</object>
	<object>
		<name>Fresa</name>
		<pose>Unspecified</pose>
		<truncated>0</truncated>
		<difficult>0</difficult>
		<bndbox>
			<xmin>74</xmin>
			<ymin>37</ymin>
			<xmax>119</xmax>
			<ymax>87</ymax>
		</bndbox>
	</object>
	<object>
		<name>Fresa</name>
		<pose>Unspecified</pose>
		<truncated>1</truncated>
		<difficult>0</difficult>
		<bndbox>
			<xmin>1</xmin>
			<ymin>35</ymin>
			<xmax>42</xmax>
			<ymax>86</ymax>
		</bndbox>
	</object>
	<object>
		<name>Fresa</name>
		<pose>Unspecified</pose>
		<truncated>0</truncated>
		<difficult>0</difficult>
		<bndbox>
			<xmin>30</xmin>
			<ymin>49</ymin>
			<xmax>70</xmax>
			<ymax>98</ymax>
		</bndbox>
	</object>
	<object>
		<name>Fresa</name>
		<pose>Unspecified</pose>
		<truncated>1</truncated>
		<difficult>0</difficult>
		<bndbox>
			<xmin>37</xmin>
			<ymin>90</ymin>
			<xmax>80</xmax>
			<ymax>120</ymax>
		</bndbox>
	</object>
	<object>
		<name>Fresa</name>
		<pose>Unspecified</pose>
		<truncated>1</truncated>
		<difficult>0</difficult>
		<bndbox>
			<xmin>1</xmin>
			<ymin>86</ymin>
			<xmax>33</xmax>
			<ymax>115</ymax>
		</bndbox>
	</object>
	<object>
		<name>Fresa</name>
		<pose>Unspecified</pose>
		<truncated>1</truncated>
		<difficult>0</difficult>
		<bndbox>
			<xmin>11</xmin>
			<ymin>105</ymin>
			<xmax>41</xmax>
			<ymax>120</ymax>
		</bndbox>
	</object>
	<object>
		<name>Fresa</name>
		<pose>Unspecified</pose>
		<truncated>0</truncated>
		<difficult>0</difficult>
		<bndbox>
			<xmin>74</xmin>
			<ymin>87</ymin>
			<xmax>100</xmax>
			<ymax>116</ymax>
		</bndbox>
	</object>
	<object>
		<name>Fresa</name>
		<pose>Unspecified</pose>
		<truncated>1</truncated>
		<difficult>0</difficult>
		<bndbox>
			<xmin>91</xmin>
			<ymin>98</ymin>
			<xmax>120</xmax>
			<ymax>120</ymax>
		</bndbox>
	</object>
</annotation>
