<annotation>
	<folder>images</folder>
	<filename>900.jpg</filename>
	<path>/home/dcampoamor/tensorflow_frutas_environment/deteccion_objetos/images/900.jpg</path>
	<source>
		<database>Unknown</database>
	</source>
	<size>
		<width>300</width>
		<height>300</height>
		<depth>3</depth>
	</size>
	<segmented>0</segmented>
	<object>
		<name>Fresa</name>
		<pose>Unspecified</pose>
		<truncated>0</truncated>
		<difficult>0</difficult>
		<bndbox>
			<xmin>176</xmin>
			<ymin>37</ymin>
			<xmax>280</xmax>
			<ymax>143</ymax>
		</bndbox>
	</object>
	<object>
		<name>Fresa</name>
		<pose>Unspecified</pose>
		<truncated>0</truncated>
		<difficult>0</difficult>
		<bndbox>
			<xmin>104</xmin>
			<ymin>149</ymin>
			<xmax>188</xmax>
			<ymax>244</ymax>
		</bndbox>
	</object>
	<object>
		<name>Fresa</name>
		<pose>Unspecified</pose>
		<truncated>0</truncated>
		<difficult>0</difficult>
		<bndbox>
			<xmin>178</xmin>
			<ymin>165</ymin>
			<xmax>270</xmax>
			<ymax>270</ymax>
		</bndbox>
	</object>
</annotation>
