<annotation>
	<folder>images</folder>
	<filename>976.jpg</filename>
	<path>/home/dcampoamor/tensorflow_frutas_environment/deteccion_objetos/images/976.jpg</path>
	<source>
		<database>Unknown</database>
	</source>
	<size>
		<width>173</width>
		<height>168</height>
		<depth>3</depth>
	</size>
	<segmented>0</segmented>
	<object>
		<name>Fresa</name>
		<pose>Unspecified</pose>
		<truncated>0</truncated>
		<difficult>0</difficult>
		<bndbox>
			<xmin>3</xmin>
			<ymin>114</ymin>
			<xmax>57</xmax>
			<ymax>167</ymax>
		</bndbox>
	</object>
	<object>
		<name>Fresa</name>
		<pose>Unspecified</pose>
		<truncated>0</truncated>
		<difficult>0</difficult>
		<bndbox>
			<xmin>71</xmin>
			<ymin>87</ymin>
			<xmax>126</xmax>
			<ymax>137</ymax>
		</bndbox>
	</object>
	<object>
		<name>Fresa</name>
		<pose>Unspecified</pose>
		<truncated>1</truncated>
		<difficult>0</difficult>
		<bndbox>
			<xmin>54</xmin>
			<ymin>129</ymin>
			<xmax>111</xmax>
			<ymax>168</ymax>
		</bndbox>
	</object>
	<object>
		<name>Fresa</name>
		<pose>Unspecified</pose>
		<truncated>0</truncated>
		<difficult>0</difficult>
		<bndbox>
			<xmin>5</xmin>
			<ymin>59</ymin>
			<xmax>68</xmax>
			<ymax>124</ymax>
		</bndbox>
	</object>
	<object>
		<name>Fresa</name>
		<pose>Unspecified</pose>
		<truncated>0</truncated>
		<difficult>0</difficult>
		<bndbox>
			<xmin>110</xmin>
			<ymin>53</ymin>
			<xmax>159</xmax>
			<ymax>107</ymax>
		</bndbox>
	</object>
	<object>
		<name>Fresa</name>
		<pose>Unspecified</pose>
		<truncated>0</truncated>
		<difficult>0</difficult>
		<bndbox>
			<xmin>123</xmin>
			<ymin>97</ymin>
			<xmax>170</xmax>
			<ymax>155</ymax>
		</bndbox>
	</object>
	<object>
		<name>Fresa</name>
		<pose>Unspecified</pose>
		<truncated>1</truncated>
		<difficult>0</difficult>
		<bndbox>
			<xmin>1</xmin>
			<ymin>35</ymin>
			<xmax>47</xmax>
			<ymax>75</ymax>
		</bndbox>
	</object>
	<object>
		<name>Fresa</name>
		<pose>Unspecified</pose>
		<truncated>0</truncated>
		<difficult>0</difficult>
		<bndbox>
			<xmin>20</xmin>
			<ymin>8</ymin>
			<xmax>60</xmax>
			<ymax>52</ymax>
		</bndbox>
	</object>
	<object>
		<name>Fresa</name>
		<pose>Unspecified</pose>
		<truncated>0</truncated>
		<difficult>0</difficult>
		<bndbox>
			<xmin>86</xmin>
			<ymin>20</ymin>
			<xmax>138</xmax>
			<ymax>77</ymax>
		</bndbox>
	</object>
</annotation>
